odoo/addons/stock_inventory_tier_validation/README.rst
odoo/addons/stock_inventory_tier_validation/__init__.py
odoo/addons/stock_inventory_tier_validation/__manifest__.py
odoo/addons/stock_inventory_tier_validation/i18n/it.po
odoo/addons/stock_inventory_tier_validation/i18n/stock_inventory_tier_validation.pot
odoo/addons/stock_inventory_tier_validation/models/__init__.py
odoo/addons/stock_inventory_tier_validation/models/stock_inventory.py
odoo/addons/stock_inventory_tier_validation/models/tier_definition.py
odoo/addons/stock_inventory_tier_validation/readme/CONFIGURE.rst
odoo/addons/stock_inventory_tier_validation/readme/CONTRIBUTORS.rst
odoo/addons/stock_inventory_tier_validation/readme/DESCRIPTION.rst
odoo/addons/stock_inventory_tier_validation/readme/INSTALL.rst
odoo/addons/stock_inventory_tier_validation/readme/USAGE.rst
odoo/addons/stock_inventory_tier_validation/static/description/icon.png
odoo/addons/stock_inventory_tier_validation/static/description/index.html
odoo/addons/stock_inventory_tier_validation/tests/__init__.py
odoo/addons/stock_inventory_tier_validation/tests/test_tier_validation.py
odoo/addons/stock_inventory_tier_validation/views/stock_inventory_views.xml
odoo14_addon_stock_inventory_tier_validation-14.0.1.0.1.dev4.dist-info/METADATA
odoo14_addon_stock_inventory_tier_validation-14.0.1.0.1.dev4.dist-info/WHEEL
odoo14_addon_stock_inventory_tier_validation-14.0.1.0.1.dev4.dist-info/top_level.txt
odoo14_addon_stock_inventory_tier_validation-14.0.1.0.1.dev4.dist-info/RECORD
